linkbudget/__init__.py
linkbudget/antenna.py
linkbudget/calc.py
linkbudget/cli.py
linkbudget/constants.py
linkbudget/pointing.py
linkbudget/propagation.py
linkbudget/test_antenna.py
linkbudget/test_calc.py
linkbudget/test_cli.py
linkbudget/test_pointing.py
linkbudget/test_propagation.py
linkbudget/test_util.py
linkbudget/util.py
link_budget-0.1.10.dist-info/LICENSE
link_budget-0.1.10.dist-info/METADATA
link_budget-0.1.10.dist-info/WHEEL
link_budget-0.1.10.dist-info/entry_points.txt
link_budget-0.1.10.dist-info/top_level.txt
link_budget-0.1.10.dist-info/RECORD
