Metadata-Version: 2.1
Name: link-budget
Version: 0.1.10
Summary: Link budget calculator for satellite and radar systems
Home-page: https://github.com/igorauad/link-budget
Author: Igor Freire
Author-email: igor@blockstream.com
License: UNKNOWN
Platform: UNKNOWN
Classifier: Programming Language :: Python :: 3
Classifier: Programming Language :: Python :: 3 :: Only
Classifier: License :: OSI Approved :: GNU General Public License v3 (GPLv3)
Requires-Python: >=3
License-File: LICENSE
Requires-Dist: itur (>=0.4.0)
Requires-Dist: numpy (>=1.19.4)
Requires-Dist: python-dateutil (>=2.7.0)
Requires-Dist: scipy (>=1.7)
Requires-Dist: skyfield (==1.42)
